CHANGELOG.md
CONTRIBUTING.md
CONTRIBUTORS.md
LICENSE
README.md
setup.cfg
setup.py
fpdf/__init__.py
fpdf/actions.py
fpdf/annotations.py
fpdf/bidi.py
fpdf/deprecation.py
fpdf/drawing.py
fpdf/encryption.py
fpdf/enums.py
fpdf/errors.py
fpdf/fonts.py
fpdf/fpdf.py
fpdf/graphics_state.py
fpdf/html.py
fpdf/image_datastructures.py
fpdf/image_parsing.py
fpdf/line_break.py
fpdf/linearization.py
fpdf/outline.py
fpdf/output.py
fpdf/prefs.py
fpdf/recorder.py
fpdf/sign.py
fpdf/structure_tree.py
fpdf/svg.py
fpdf/syntax.py
fpdf/table.py
fpdf/template.py
fpdf/text_region.py
fpdf/transitions.py
fpdf/unicode_script.py
fpdf/util.py
whoisltd_fpdf2.egg-info/PKG-INFO
whoisltd_fpdf2.egg-info/SOURCES.txt
whoisltd_fpdf2.egg-info/dependency_links.txt
whoisltd_fpdf2.egg-info/requires.txt
whoisltd_fpdf2.egg-info/top_level.txt