Metadata-Version: 2.1
Name: whoisltd-fpdf2
Version: 2.8.1
Summary: Simple & fast PDF generation for Python
Home-page: https://py-pdf.github.io/fpdf2/
Author: whoisltd
Author-email: tiendat.le129@gmail.com
Maintainer: Lucas Cimon
License: LGPL-3.0-or-later
Download-URL: https://github.com/py-pdf/fpdf2/tarball/2.8.1
Project-URL: Documentation, https://py-pdf.github.io/fpdf2/
Project-URL: Code, https://github.com/py-pdf/fpdf2
Project-URL: Issue tracker, https://github.com/py-pdf/fpdf2/issues
Keywords: pdf,unicode,png,jpg,ttf,barcode
Platform: UNKNOWN
Classifier: Development Status :: 5 - Production/Stable
Classifier: Intended Audience :: Developers
Classifier: License :: OSI Approved :: GNU Lesser General Public License v3 (LGPLv3)
Classifier: Programming Language :: Python
Classifier: Programming Language :: Python :: 3.7
Classifier: Programming Language :: Python :: 3.8
Classifier: Programming Language :: Python :: 3.9
Classifier: Programming Language :: Python :: 3.10
Classifier: Programming Language :: Python :: 3.11
Classifier: Programming Language :: Python :: 3.12
Classifier: Operating System :: OS Independent
Classifier: Topic :: Printing
Classifier: Topic :: Software Development :: Libraries :: Python Modules
Classifier: Topic :: Text Processing :: Markup
Classifier: Topic :: Multimedia :: Graphics
Classifier: Topic :: Multimedia :: Graphics :: Presentation
Requires-Python: >=3.7
